flask_restless_swagger/__init__.py
flask_restless_swagger/static/swagger-ui/index.html
flask_restless_swagger/static/swagger-ui/o2c.html
flask_restless_swagger/static/swagger-ui/swagger-ui.js
flask_restless_swagger/static/swagger-ui/swagger-ui.min.js
flask_restless_swagger/static/swagger-ui/css/print.css
flask_restless_swagger/static/swagger-ui/css/reset.css
flask_restless_swagger/static/swagger-ui/css/screen.css
flask_restless_swagger/static/swagger-ui/css/style.css
flask_restless_swagger/static/swagger-ui/css/typography.css
flask_restless_swagger/static/swagger-ui/fonts/droid-sans-v6-latin-700.eot
flask_restless_swagger/static/swagger-ui/fonts/droid-sans-v6-latin-700.svg
flask_restless_swagger/static/swagger-ui/fonts/droid-sans-v6-latin-700.ttf
flask_restless_swagger/static/swagger-ui/fonts/droid-sans-v6-latin-700.woff
flask_restless_swagger/static/swagger-ui/fonts/droid-sans-v6-latin-700.woff2
flask_restless_swagger/static/swagger-ui/fonts/droid-sans-v6-latin-regular.eot
flask_restless_swagger/static/swagger-ui/fonts/droid-sans-v6-latin-regular.svg
flask_restless_swagger/static/swagger-ui/fonts/droid-sans-v6-latin-regular.ttf
flask_restless_swagger/static/swagger-ui/fonts/droid-sans-v6-latin-regular.woff
flask_restless_swagger/static/swagger-ui/fonts/droid-sans-v6-latin-regular.woff2
flask_restless_swagger/static/swagger-ui/images/explorer_icons.png
flask_restless_swagger/static/swagger-ui/images/favicon-16x16.png
flask_restless_swagger/static/swagger-ui/images/favicon-32x32.png
flask_restless_swagger/static/swagger-ui/images/favicon.ico
flask_restless_swagger/static/swagger-ui/images/logo_small.png
flask_restless_swagger/static/swagger-ui/images/pet_store_api.png
flask_restless_swagger/static/swagger-ui/images/throbber.gif
flask_restless_swagger/static/swagger-ui/images/wordnik_api.png
flask_restless_swagger-0.2.1.dist-info/DESCRIPTION.rst
flask_restless_swagger-0.2.1.dist-info/METADATA
flask_restless_swagger-0.2.1.dist-info/metadata.json
flask_restless_swagger-0.2.1.dist-info/pbr.json
flask_restless_swagger-0.2.1.dist-info/RECORD
flask_restless_swagger-0.2.1.dist-info/top_level.txt
flask_restless_swagger-0.2.1.dist-info/WHEEL
