Metadata-Version: 2.0
Name: flask-restless-swagger
Version: 0.2.1
Summary: Magically create swagger documentation as you magically create your RESTful API
Home-page: https://github.com/mmessmore/flask-restless-swagger
Author: Michael Messmore
Author-email: mike@messmore.org
License: BSD
Keywords: flask-restless-swagger
Platform: UNKNOWN
Classifier: Development Status :: 2 - Pre-Alpha
Classifier: Intended Audience :: Developers
Classifier: License :: OSI Approved :: BSD License
Classifier: Natural Language :: English
Classifier: Programming Language :: Python :: 2
Classifier: Programming Language :: Python :: 2.6
Classifier: Programming Language :: Python :: 2.7
Classifier: Programming Language :: Python :: 3
Classifier: Programming Language :: Python :: 3.3
Classifier: Programming Language :: Python :: Implementation :: PyPy
Classifier: Topic :: Internet :: WWW/HTTP :: Dynamic Content
Classifier: Topic :: Software Development :: Libraries :: Python Modules
Requires-Dist: Flask (>=0.10.0)
Requires-Dist: Flask-Restless (>=0.17.0)
